kernelkit/__init__.py
kernelkit/algo.py
kernelkit/data.py
kernelkit/experimental.py
kernelkit/kernel.py
kernelkit/operator.py
kernelkit/processing.py
kernelkit/projector.py
kernelkit/toolbox_support.py
kernelkit/torch_support.py
kernelkit/cuda/__init__.py
kernelkit/cuda/cone_bp.cu
kernelkit/cuda/cone_fp.cu
kernelkit/cuda/fan_bp.cu
kernelkit/cuda/fan_fp.cu
kernelkit/geom/__init__.py
kernelkit/geom/proj.py
kernelkit/geom/vol.py
kernelkit/kernels/__init__.py
kernelkit/kernels/cone_bp.py
kernelkit/kernels/cone_fp.py
kernelkit/kernels/fanbeam.py
astra_kernelkit-1.0.0a2.post1.dist-info/LICENSE.md
astra_kernelkit-1.0.0a2.post1.dist-info/METADATA
astra_kernelkit-1.0.0a2.post1.dist-info/WHEEL
astra_kernelkit-1.0.0a2.post1.dist-info/top_level.txt
astra_kernelkit-1.0.0a2.post1.dist-info/zip-safe
astra_kernelkit-1.0.0a2.post1.dist-info/RECORD
